packagegenerator/__init__.py
packagegenerator/__main__.py
packagegenerator/main.py
packagegenerator/templates/base/pyproject.toml-tmpl
packagegenerator/templates/base/$packagename_format/__init__.py-tmpl
packagegenerator/templates/base/$packagename_format/__main__.py-tmpl
packagegenerator/templates/base/$packagename_format/main.py-tmpl
packagegenerator/templates/moreparams/pyproject.toml-tmpl
packagegenerator/templates/moreparams/$packagename_format/__init__.py-tmpl
packagegenerator/templates/moreparams/$packagename_format/__main__.py-tmpl
packagegenerator/templates/moreparams/$packagename_format/main.py-tmpl
package_gen-1.0.0.dist-info/METADATA
package_gen-1.0.0.dist-info/WHEEL
package_gen-1.0.0.dist-info/entry_points.txt
package_gen-1.0.0.dist-info/top_level.txt
package_gen-1.0.0.dist-info/RECORD
