Metadata-Version: 2.1
Name: package-gen
Version: 1.0.0
Summary: Generate python package
Author: Zhang
Project-URL: Homepage, https://github.com/suifengpiaoyang/package-gen
Classifier: Development Status :: 3 - Alpha
Classifier: Programming Language :: Python :: 3
Classifier: Programming Language :: Python :: 3.8
Classifier: Programming Language :: Python :: 3.9
Classifier: Programming Language :: Python :: 3.10
Classifier: Operating System :: OS Independent
Requires-Python: >=3.8
